exchangelib/__init__.py
exchangelib/account.py
exchangelib/attachments.py
exchangelib/configuration.py
exchangelib/credentials.py
exchangelib/errors.py
exchangelib/ewsdatetime.py
exchangelib/extended_properties.py
exchangelib/fields.py
exchangelib/indexed_properties.py
exchangelib/properties.py
exchangelib/protocol.py
exchangelib/queryset.py
exchangelib/recurrence.py
exchangelib/restriction.py
exchangelib/settings.py
exchangelib/transport.py
exchangelib/util.py
exchangelib/version.py
exchangelib/winzone.py
exchangelib/autodiscover/__init__.py
exchangelib/autodiscover/cache.py
exchangelib/autodiscover/discovery.py
exchangelib/autodiscover/protocol.py
exchangelib/folders/__init__.py
exchangelib/folders/base.py
exchangelib/folders/collections.py
exchangelib/folders/known_folders.py
exchangelib/folders/queryset.py
exchangelib/folders/roots.py
exchangelib/items/__init__.py
exchangelib/items/base.py
exchangelib/items/calendar_item.py
exchangelib/items/contact.py
exchangelib/items/item.py
exchangelib/items/message.py
exchangelib/items/post.py
exchangelib/items/task.py
exchangelib/services/__init__.py
exchangelib/services/archive_item.py
exchangelib/services/common.py
exchangelib/services/convert_id.py
exchangelib/services/copy_item.py
exchangelib/services/create_attachment.py
exchangelib/services/create_folder.py
exchangelib/services/create_item.py
exchangelib/services/create_user_configuration.py
exchangelib/services/delete_attachment.py
exchangelib/services/delete_folder.py
exchangelib/services/delete_item.py
exchangelib/services/delete_user_configuration.py
exchangelib/services/empty_folder.py
exchangelib/services/expand_dl.py
exchangelib/services/export_items.py
exchangelib/services/find_folder.py
exchangelib/services/find_item.py
exchangelib/services/find_people.py
exchangelib/services/get_attachment.py
exchangelib/services/get_delegate.py
exchangelib/services/get_events.py
exchangelib/services/get_folder.py
exchangelib/services/get_item.py
exchangelib-5.5.0.dist-info/LICENSE
exchangelib-5.5.0.dist-info/METADATA
exchangelib-5.5.0.dist-info/WHEEL
exchangelib-5.5.0.dist-info/top_level.txt
exchangelib-5.5.0.dist-info/RECORD
