Metadata-Version: 2.1
Name: exchangelib
Version: 5.5.0
Summary: Client for Microsoft Exchange Web Services (EWS)
Author-email: Erik Cederstrand <erik@cederstrand.dk>
License: BSD-2-Clause
Project-URL: Homepage, https://github.com/ecederstrand/exchangelib
Project-URL: Issues, https://github.com/ecederstrand/exchangelib/issues
Project-URL: Documentation, https://ecederstrand.github.io/exchangelib/
Project-URL: Repository, https://github.com/ecederstrand/exchangelib.git
Project-URL: Changelog, https://github.com/ecederstrand/exchangelib/blob/master/CHANGELOG.md
Keywords: autodiscover,ews,exchange,exchange-web-services,microsoft,o365,office365,outlook
Classifier: Development Status :: 5 - Production/Stable
Classifier: Topic :: Communications
Classifier: License :: OSI Approved :: BSD License
Classifier: Programming Language :: Python :: 3
Requires-Python: >=3.9
License-File: LICENSE
Requires-Dist: cached_property
Requires-Dist: defusedxml>=0.6.0
Requires-Dist: dnspython>=2.2.0
Requires-Dist: isodate
Requires-Dist: lxml>3.0
Requires-Dist: oauthlib
Requires-Dist: pygments
Requires-Dist: requests>=2.31.0
Requires-Dist: requests_ntlm>=0.2.0
Requires-Dist: requests_oauthlib
Requires-Dist: tzdata
Requires-Dist: tzlocal
Provides-Extra: kerberos
Requires-Dist: requests_gssapi; extra == "kerberos"
Provides-Extra: msal
Requires-Dist: msal; extra == "msal"
Provides-Extra: sspi
Requires-Dist: requests_negotiate_sspi; extra == "sspi"
Provides-Extra: complete
Requires-Dist: requests_gssapi; extra == "complete"
Requires-Dist: msal; extra == "complete"
Requires-Dist: requests_negotiate_sspi; extra == "complete"
